{"chunk_definitions":[{"row":16,"row_count":1,"visible":true,"expansion_state":0,"options":{"engine":"r","label":"unnamed-chunk-85"},"document_id":"E0AE4DDB","chunk_id":"cfzgwoz5cvw1f","chunk_label":"unnamed-chunk-1"},{"row":27,"row_count":1,"visible":true,"expansion_state":0,"options":{"engine":"r","label":"unnamed-chunk-86"},"document_id":"E0AE4DDB","chunk_id":"c0q8yqya9z8ph","chunk_label":"unnamed-chunk-2"},{"row":33,"row_count":1,"visible":true,"expansion_state":0,"options":{"engine":"r","label":"unnamed-chunk-87"},"document_id":"E0AE4DDB","chunk_id":"cbyahs7dscfg3","chunk_label":"unnamed-chunk-3"},{"row":39,"row_count":1,"visible":true,"expansion_state":0,"options":{"engine":"r","label":"unnamed-chunk-88"},"document_id":"E0AE4DDB","chunk_id":"cfz9wy4onku3o","chunk_label":"unnamed-chunk-4"},{"row":45,"row_count":1,"visible":true,"expansion_state":0,"options":{"engine":"r","label":"unnamed-chunk-89"},"document_id":"E0AE4DDB","chunk_id":"cp0w7c34puc5b","chunk_label":"unnamed-chunk-5"},{"row":49,"row_count":1,"visible":true,"expansion_state":0,"options":{"engine":"r","label":"unnamed-chunk-90"},"document_id":"E0AE4DDB","chunk_id":"cd3s6um16ig6t","chunk_label":"unnamed-chunk-6"},{"row":61,"row_count":1,"visible":true,"expansion_state":0,"options":{"engine":"r","label":"unnamed-chunk-91"},"document_id":"E0AE4DDB","chunk_id":"cs4qmux78qu7b","chunk_label":"unnamed-chunk-7"},{"row":70,"row_count":1,"visible":true,"expansion_state":0,"options":{"engine":"r","label":"unnamed-chunk-92"},"document_id":"E0AE4DDB","chunk_id":"cud5n45z6l1kl","chunk_label":"unnamed-chunk-8"},{"row":74,"row_count":1,"visible":true,"expansion_state":0,"options":{"engine":"r","label":"unnamed-chunk-93"},"document_id":"E0AE4DDB","chunk_id":"cen8mwbrcdz8r","chunk_label":"unnamed-chunk-9"},{"row":78,"row_count":1,"visible":true,"expansion_state":0,"options":{"engine":"r","label":"unnamed-chunk-94"},"document_id":"E0AE4DDB","chunk_id":"cl2tblltpwqrg","chunk_label":"unnamed-chunk-10"},{"row":95,"row_count":1,"visible":true,"expansion_state":0,"options":{"engine":"r","label":"unnamed-chunk-95"},"document_id":"E0AE4DDB","chunk_id":"c8t0o95fmjgo3","chunk_label":"unnamed-chunk-11"},{"row":99,"row_count":1,"visible":true,"expansion_state":0,"options":{"engine":"r","label":"unnamed-chunk-96"},"document_id":"E0AE4DDB","chunk_id":"clggv9g9basht","chunk_label":"unnamed-chunk-12"},{"row":103,"row_count":1,"visible":true,"expansion_state":0,"options":{"engine":"r","label":"unnamed-chunk-97"},"document_id":"E0AE4DDB","chunk_id":"c2slqw15kgprg","chunk_label":"unnamed-chunk-13"},{"row":109,"row_count":1,"visible":true,"expansion_state":0,"options":{"engine":"r","label":"unnamed-chunk-98"},"document_id":"E0AE4DDB","chunk_id":"c7uq8tj2f0kn3","chunk_label":"unnamed-chunk-14"},{"row":121,"row_count":1,"visible":true,"expansion_state":0,"options":{"engine":"r","label":"unnamed-chunk-99"},"document_id":"E0AE4DDB","chunk_id":"c4c08h4eivvxj","chunk_label":"unnamed-chunk-15"},{"row":125,"row_count":1,"visible":true,"expansion_state":0,"options":{"engine":"r","label":"unnamed-chunk-100"},"document_id":"E0AE4DDB","chunk_id":"c5fwl0u84v1cd","chunk_label":"unnamed-chunk-16"},{"row":129,"row_count":1,"visible":true,"expansion_state":0,"options":{"engine":"r","label":"unnamed-chunk-101"},"document_id":"E0AE4DDB","chunk_id":"cv83zrhfxuj6w","chunk_label":"unnamed-chunk-17"},{"row":135,"row_count":1,"visible":true,"expansion_state":0,"options":{"engine":"r","label":"unnamed-chunk-102"},"document_id":"E0AE4DDB","chunk_id":"c3r2yn629toqc","chunk_label":"unnamed-chunk-18"},{"row":142,"row_count":1,"visible":true,"expansion_state":0,"options":{"engine":"r","label":"unnamed-chunk-103"},"document_id":"E0AE4DDB","chunk_id":"cw67h3hvm4v2r","chunk_label":"unnamed-chunk-19"},{"row":154,"row_count":1,"visible":true,"expansion_state":0,"options":{"engine":"r","label":"unnamed-chunk-104"},"document_id":"E0AE4DDB","chunk_id":"coqa3icfqj9xv","chunk_label":"unnamed-chunk-20"},{"row":160,"row_count":1,"visible":true,"expansion_state":0,"options":{"engine":"r","label":"unnamed-chunk-105"},"document_id":"E0AE4DDB","chunk_id":"cfb1tu6nc4bsd","chunk_label":"unnamed-chunk-21"},{"row":174,"row_count":1,"visible":true,"expansion_state":0,"options":{"engine":"r","label":"unnamed-chunk-106"},"document_id":"E0AE4DDB","chunk_id":"cs7gtq1tvktjc","chunk_label":"unnamed-chunk-22"},{"row":180,"row_count":1,"visible":true,"expansion_state":0,"options":{"engine":"r","label":"unnamed-chunk-107"},"document_id":"E0AE4DDB","chunk_id":"cfy5rc179jrg4","chunk_label":"unnamed-chunk-23"},{"row":192,"row_count":1,"visible":true,"expansion_state":0,"options":{"engine":"r","label":"unnamed-chunk-108"},"document_id":"E0AE4DDB","chunk_id":"ci7407r92kpow","chunk_label":"unnamed-chunk-24"},{"row":198,"row_count":1,"visible":true,"expansion_state":0,"options":{"engine":"r","label":"unnamed-chunk-109"},"document_id":"E0AE4DDB","chunk_id":"cddyh2oumfpjt","chunk_label":"unnamed-chunk-25"},{"row":208,"row_count":1,"visible":true,"expansion_state":0,"options":{"engine":"r","label":"unnamed-chunk-110"},"document_id":"E0AE4DDB","chunk_id":"cdtefg7b9leaf","chunk_label":"unnamed-chunk-26"},{"row":218,"row_count":1,"visible":true,"expansion_state":0,"options":{"engine":"r","label":"unnamed-chunk-111"},"document_id":"E0AE4DDB","chunk_id":"crhqm5uhr66zv","chunk_label":"unnamed-chunk-27"},{"row":228,"row_count":1,"visible":true,"expansion_state":0,"options":{"engine":"r","label":"unnamed-chunk-112"},"document_id":"E0AE4DDB","chunk_id":"cprq7dgwk8vwj","chunk_label":"unnamed-chunk-28"},{"row":238,"row_count":1,"visible":true,"expansion_state":0,"options":{"engine":"r","label":"unnamed-chunk-113"},"document_id":"E0AE4DDB","chunk_id":"c8vir37zhq479","chunk_label":"unnamed-chunk-29"},{"row":248,"row_count":1,"visible":true,"expansion_state":0,"options":{"engine":"r","label":"unnamed-chunk-114"},"document_id":"E0AE4DDB","chunk_id":"chg78m67jmfmc","chunk_label":"unnamed-chunk-30"},{"row":258,"row_count":1,"visible":true,"expansion_state":0,"options":{"engine":"r","label":"unnamed-chunk-115"},"document_id":"E0AE4DDB","chunk_id":"cjpkvgqzpgrno","chunk_label":"unnamed-chunk-31"},{"row":268,"row_count":1,"visible":true,"expansion_state":0,"options":{"engine":"r","label":"unnamed-chunk-116"},"document_id":"E0AE4DDB","chunk_id":"c7bonksp2apbt","chunk_label":"unnamed-chunk-32"},{"row":278,"row_count":1,"visible":true,"expansion_state":0,"options":{"engine":"r","label":"unnamed-chunk-117"},"document_id":"E0AE4DDB","chunk_id":"c0wvrmk33qfpr","chunk_label":"unnamed-chunk-33"},{"row":287,"row_count":1,"visible":true,"expansion_state":0,"options":{"engine":"r","label":"unnamed-chunk-118"},"document_id":"E0AE4DDB","chunk_id":"cw770chf5zv71","chunk_label":"unnamed-chunk-34"},{"row":296,"row_count":1,"visible":true,"expansion_state":0,"options":{"engine":"r","label":"unnamed-chunk-119"},"document_id":"E0AE4DDB","chunk_id":"cbl54a6hihtzm","chunk_label":"unnamed-chunk-35"},{"row":304,"row_count":1,"visible":true,"expansion_state":0,"options":{"engine":"r","label":"unnamed-chunk-120"},"document_id":"E0AE4DDB","chunk_id":"cptbsxyyiv6pg","chunk_label":"unnamed-chunk-36"},{"row":313,"row_count":1,"visible":true,"expansion_state":0,"options":{"engine":"r","label":"unnamed-chunk-121"},"document_id":"E0AE4DDB","chunk_id":"cxz2lx1o3bemm","chunk_label":"unnamed-chunk-37"},{"row":322,"row_count":1,"visible":true,"expansion_state":0,"options":{"engine":"r","label":"unnamed-chunk-122"},"document_id":"E0AE4DDB","chunk_id":"czwhkz1yxt0me","chunk_label":"unnamed-chunk-38"},{"row":331,"row_count":1,"visible":true,"expansion_state":0,"options":{"engine":"r","label":"unnamed-chunk-123"},"document_id":"E0AE4DDB","chunk_id":"c6zan3ztf3fnn","chunk_label":"unnamed-chunk-39"},{"row":340,"row_count":1,"visible":true,"expansion_state":0,"options":{"engine":"r","label":"unnamed-chunk-124"},"document_id":"E0AE4DDB","chunk_id":"cnq9lfeq4v8va","chunk_label":"unnamed-chunk-40"},{"row":349,"row_count":1,"visible":true,"expansion_state":0,"options":{"engine":"r","label":"unnamed-chunk-125"},"document_id":"E0AE4DDB","chunk_id":"cuzhkftj1odu8","chunk_label":"unnamed-chunk-41"},{"row":355,"row_count":1,"visible":true,"expansion_state":0,"options":{"engine":"r","label":"unnamed-chunk-126"},"document_id":"E0AE4DDB","chunk_id":"c71i8gl6v3130","chunk_label":"unnamed-chunk-42"},{"row":359,"row_count":1,"visible":true,"expansion_state":0,"options":{"engine":"r","label":"unnamed-chunk-127"},"document_id":"E0AE4DDB","chunk_id":"cpccdb8jb4q1a","chunk_label":"unnamed-chunk-43"}],"doc_write_time":1701107496}